torchutils/__init__.py
torchutils/_flops.py
torchutils/_validate.py
torchutils/_version.py
torchutils/checkpoint.py
torchutils/datasets.py
torchutils/learningrate.py
torchutils/metrics.py
torchutils/models.py
torchutils/utils.py
torchutils/visualize.py
torchutils-0.0.4.dist-info/LICENSE
torchutils-0.0.4.dist-info/METADATA
torchutils-0.0.4.dist-info/WHEEL
torchutils-0.0.4.dist-info/top_level.txt
torchutils-0.0.4.dist-info/RECORD
