Metadata-Version: 2.1
Name: torchutils
Version: 0.0.4
Summary: PyTorch utility APIs.
Home-page: https://github.com/anjandeepsahni/torchutils.git
Author: Anjandeep Singh Sahni
Author-email: sahni.anjandeep@gmail.com
License: MIT
Keywords: machine-learning deep-learning pytorch neuralnetwork
Platform: UNKNOWN
Classifier: Programming Language :: Python :: 3
Classifier: License :: OSI Approved :: MIT License
Classifier: Operating System :: OS Independent
Requires-Dist: torch (>=1.0.0)
Requires-Dist: numpy (>=1.16.2)
Requires-Dist: matplotlib (>=3.0.3)
